LICENSE
MANIFEST.in
README.md
requirements.txt
setup.py
cpctl/__init__.py
cpctl/at.py
cpctl/cli.py
cpctl/utils.py
cpctl.egg-info/PKG-INFO
cpctl.egg-info/SOURCES.txt
cpctl.egg-info/dependency_links.txt
cpctl.egg-info/entry_points.txt
cpctl.egg-info/requires.txt
cpctl.egg-info/top_level.txt